{
  "checkpoint_id": "ckpt_8522556b",
  "workflow_id": "m55IZ1mIJJT5mmYxF1pb",
  "execution_id": "3773aa2d-a42c-487c-94a9-ac39c4419820",
  "checkpoint_type": "error",
  "current_node_id": "",
  "current_data": {
    "demoInput": "Hello from workflow editor!"
  },
  "node_logs": [],
  "variables": {},
  "visited_nodes": [],
  "pending_nodes": [],
  "created_at": "2026-02-22T14:31:56.445695",
  "execution_time_ms": 0.0,
  "checkpoint_size_bytes": 0,
  "last_successful_node": null,
  "last_error": "'targetNodeId'"
}